{"doctors": [
    {
        "id": 581506,
        "isActive": false,
        "isHidden": true,
        "isFavorite": false,
        "name": "Авдеев Эльдар Нурисламович",
        "surname": "",
        "alias": "Avdeev_Eldar",
        "sex": 1,
        "url": "/doctor/Avdeev_Eldar",
        "logo": null,
        "rectangularImage": null,
        "image": "",
        "mobileImage": "",
        "tipMessage": "",
        "departure": false,
        "kidsReception": false,
        "rating": {
            "label": "Превосходный",
            "rating": 0,
            "doctorRating": 8.8
        },
        "popularityRating": 0,
        "doctorExt": false,
        "index": 0,
        "ratingType": "stars_and_label",
        "countReviewsString": "0 отзывов",
        "countReviews": 0,
        "topReviewsPercent": 0,
        "rank": null,
        "specialities": [
            {
                "id": 157,
                "name": "Рентгенолог",
                "alias": "rentgenolog"
            }
        ],
        "tooltipPrices": [
            {
                "clinicAddress": "г. Ижевск, ул. Ленина, д. 87Б",
                "price": null,
                "specialPrice": null,
                "sectorNames": "Рентгенолог"
            }
        ],
        "standardPrices": [],
        "highlight": 0,
        "clinics": {
            "93516": {
                "active": true,
                "selected": true,
                "id": 93516,
                "name": "Республиканский клинико-диагностический центр Министерства Здравоохранения Удмуртской Республики",
                "alias": "respublikanskiy_kliniko-diagnosticheskiy_tsentr_ministerstva_zdravoohraneniya_udmurtskoy_respubliki",
                "url": "/clinic/respublikanskiy_kliniko-diagnosticheskiy_tsentr_ministerstva_zdravoohraneniya_udmurtskoy_respubliki",
                "phone": "8 (495) 125-29-52",
                "price": null,
                "specialPrice": null,
                "coords": [
                    56.849118,
                    53.251429
                ],
                "isPrivateDoctor": false,
                "isRecommended": false,
                "notEmptySlots": false,
                "address": {
                    "street": "ул. Ленина",
                    "house": "д. 87Б",
                    "fullAddress": "г. Ижевск, ул. Ленина, д. 87Б"
                },
                "cityId": 0,
                "diagnosticsName": null,
                "diagnosticsPrice": null,
                "stations": null,
                "hasYandexCashBack": false,
                "receptionPrices": {
                    "clinic": {
                        "price": null,
                        "specialPrice": null
                    }
                },
                "isPriorityPartner": false,
                "adultsReception": 1,
                "kidsReception": 0,
                "kidsReceptionAgeRange": []
            }
        },
        "slots": [],
        "categoryId": 2,
        "categoryTitle": "Врач первой категории",
        "experience": 32,
        "degreeId": 0,
        "degreeAbbreviation": "",
        "degreeTitle": "",
        "hasPromoPrice": false,
        "hasStandardPrice": false,
        "hasYandexCashBack": false,
        "departurePrice": null,
        "tooltipText": "Стоимость указана за первичный приём.\nВ неё не входит стоимость дополнительных исследований и выезда на дом.",
        "seoSlotTipText": "",
        "isEnabledPromoPrice": false,
        "review": [],
        "specAccommodationIndex": null,
        "surgeryInfo": null
    },
    {
        "id": 581518,
        "isActive": false,
        "isHidden": true,
        "isFavorite": false,
        "name": "Решетникова Ольга Викторовна",
        "surname": "",
        "alias": "Reshetnikova_Olga_3",
        "sex": 2,
        "url": "/doctor/Reshetnikova_Olga_3",
        "logo": null,
        "rectangularImage": null,
        "image": "",
        "mobileImage": "",
        "tipMessage": "",
        "departure": false,
        "kidsReception": false,
        "rating": {
            "label": "Очень хороший",
            "rating": 0,
            "doctorRating": 8.6
        },
        "popularityRating": 0,
        "doctorExt": false,
        "index": 1,
        "ratingType": "stars_and_label",
        "countReviewsString": "0 отзывов",
        "countReviews": 0,
        "topReviewsPercent": 0,
        "rank": null,
        "specialities": [
            {
                "id": 181,
                "name": "Врач функциональной диагностики ",
                "alias": "vrach-funkcionalnoy-diagnostiki"
            }
        ],
        "tooltipPrices": [
            {
                "clinicAddress": "г. Ижевск, ул. Ленина, д. 87Б",
                "price": null,
                "specialPrice": null,
                "sectorNames": "Врач функциональной диагностики "
            }
        ],
        "standardPrices": [],
        "highlight": 0,
        "clinics": {
            "93516": {
                "active": true,
                "selected": true,
                "id": 93516,
                "name": "Республиканский клинико-диагностический центр Министерства Здравоохранения Удмуртской Республики",
                "alias": "respublikanskiy_kliniko-diagnosticheskiy_tsentr_ministerstva_zdravoohraneniya_udmurtskoy_respubliki",
                "url": "/clinic/respublikanskiy_kliniko-diagnosticheskiy_tsentr_ministerstva_zdravoohraneniya_udmurtskoy_respubliki",
                "phone": "8 (495) 125-29-52",
                "price": null,
                "specialPrice": null,
                "coords": [
                    56.849118,
                    53.251429
                ],
                "isPrivateDoctor": false,
                "isRecommended": false,
                "notEmptySlots": false,
                "address": {
                    "street": "ул. Ленина",
                    "house": "д. 87Б",
                    "fullAddress": "г. Ижевск, ул. Ленина, д. 87Б"
                },
                "cityId": 0,
                "diagnosticsName": null,
                "diagnosticsPrice": null,
                "stations": null,
                "hasYandexCashBack": false,
                "receptionPrices": {
                    "clinic": {
                        "price": null,
                        "specialPrice": null
                    }
                },
                "isPriorityPartner": false,
                "adultsReception": 1,
                "kidsReception": 0,
                "kidsReceptionAgeRange": []
            }
        },
        "slots": [],
        "categoryId": 1,
        "categoryTitle": "Врач высшей категории",
        "experience": 28,
        "degreeId": 0,
        "degreeAbbreviation": "",
        "degreeTitle": "",
        "hasPromoPrice": false,
        "hasStandardPrice": false,
        "hasYandexCashBack": false,
        "departurePrice": null,
        "tooltipText": "Стоимость указана за первичный приём.\nВ неё не входит стоимость дополнительных исследований и выезда на дом.",
        "seoSlotTipText": "",
        "isEnabledPromoPrice": false,
        "review": [],
        "specAccommodationIndex": null,
        "surgeryInfo": null
    },
    {
        "id": 581520,
        "isActive": false,
        "isHidden": true,
        "isFavorite": false,
        "name": "Сурнина Ольга Владимировна",
        "surname": "",
        "alias": "Surnina_Olga",
        "sex": 2,
        "url": "/doctor/Surnina_Olga",
        "logo": null,
        "rectangularImage": null,
        "image": "",
        "mobileImage": "",
        "tipMessage": "",
        "departure": false,
        "kidsReception": false,
        "rating": {
            "label": "Превосходный",
            "rating": 0,
            "doctorRating": 8.9
        },
        "popularityRating": 0,
        "doctorExt": false,
        "index": 2,
        "ratingType": "stars_and_label",
        "countReviewsString": "0 отзывов",
        "countReviews": 0,
        "topReviewsPercent": 0,
        "rank": null,
        "specialities": [
            {
                "id": 100,
                "name": "УЗИ-специалист",
                "alias": "vrach_uzi"
            }
        ],
        "tooltipPrices": [
            {
                "clinicAddress": "г. Ижевск, ул. Ленина, д. 87Б",
                "price": null,
                "specialPrice": null,
                "sectorNames": "УЗИ-специалист"
            }
        ],
        "standardPrices": [],
        "highlight": 0,
        "clinics": {
            "93516": {
                "active": true,
                "selected": true,
                "id": 93516,
                "name": "Республиканский клинико-диагностический центр Министерства Здравоохранения Удмуртской Республики",
                "alias": "respublikanskiy_kliniko-diagnosticheskiy_tsentr_ministerstva_zdravoohraneniya_udmurtskoy_respubliki",
                "url": "/clinic/respublikanskiy_kliniko-diagnosticheskiy_tsentr_ministerstva_zdravoohraneniya_udmurtskoy_respubliki",
                "phone": "8 (495) 125-29-52",
                "price": null,
                "specialPrice": null,
                "coords": [
                    56.849118,
                    53.251429
                ],
                "isPrivateDoctor": false,
                "isRecommended": false,
                "notEmptySlots": false,
                "address": {
                    "street": "ул. Ленина",
                    "house": "д. 87Б",
                    "fullAddress": "г. Ижевск, ул. Ленина, д. 87Б"
                },
                "cityId": 0,
                "diagnosticsName": null,
                "diagnosticsPrice": null,
                "stations": null,
                "hasYandexCashBack": false,
                "receptionPrices": {
                    "clinic": {
                        "price": null,
                        "specialPrice": null
                    }
                },
                "isPriorityPartner": false,
                "adultsReception": 1,
                "kidsReception": 0,
                "kidsReceptionAgeRange": []
            }
        },
        "slots": [],
        "categoryId": 1,
        "categoryTitle": "Врач высшей категории",
        "experience": 25,
        "degreeId": 1,
        "degreeAbbreviation": "к.м.н.",
        "degreeTitle": "Кандидат медицинских наук",
        "hasPromoPrice": false,
        "hasStandardPrice": false,
        "hasYandexCashBack": false,
        "departurePrice": null,
        "tooltipText": "Стоимость указана за первичный приём.\nВ неё не входит стоимость дополнительных исследований и выезда на дом.",
        "seoSlotTipText": "",
        "isEnabledPromoPrice": false,
        "review": [],
        "specAccommodationIndex": null,
        "surgeryInfo": null
    },
    {
        "id": 581524,
        "isActive": false,
        "isHidden": true,
        "isFavorite": false,
        "name": "Мыкольников Алексей Владимирович",
        "surname": "",
        "alias": "Mykolnikov_Aleksey",
        "sex": 1,
        "url": "/doctor/Mykolnikov_Aleksey",
        "logo": null,
        "rectangularImage": null,
        "image": "",
        "mobileImage": "",
        "tipMessage": "",
        "departure": false,
        "kidsReception": false,
        "rating": {
            "label": "Очень хороший",
            "rating": 0,
            "doctorRating": 8.6
        },
        "popularityRating": 0,
        "doctorExt": false,
        "index": 3,
        "ratingType": "stars_and_label",
        "countReviewsString": "0 отзывов",
        "countReviews": 0,
        "topReviewsPercent": 0,
        "rank": null,
        "specialities": [
            {
                "id": 254,
                "name": "Ангиохирург",
                "alias": "angiohirurg"
            },
            {
                "id": 145,
                "name": "Сосудистый хирург",
                "alias": "sosudistij_hirurg"
            },
            {
                "id": 94,
                "name": "Флеболог",
                "alias": "flebolog"
            }
        ],
        "tooltipPrices": [
            {
                "clinicAddress": "г. Ижевск, ул. Ленина, д. 87Б",
                "price": null,
                "specialPrice": null,
                "sectorNames": "Флеболог, Сосудистый хирург, Ангиохирург"
            }
        ],
        "standardPrices": [],
        "highlight": 0,
        "clinics": {
            "93516": {
                "active": true,
                "selected": true,
                "id": 93516,
                "name": "Республиканский клинико-диагностический центр Министерства Здравоохранения Удмуртской Республики",
                "alias": "respublikanskiy_kliniko-diagnosticheskiy_tsentr_ministerstva_zdravoohraneniya_udmurtskoy_respubliki",
                "url": "/clinic/respublikanskiy_kliniko-diagnosticheskiy_tsentr_ministerstva_zdravoohraneniya_udmurtskoy_respubliki",
                "phone": "8 (495) 125-29-52",
                "price": null,
                "specialPrice": null,
                "coords": [
                    56.849118,
                    53.251429
                ],
                "isPrivateDoctor": false,
                "isRecommended": false,
                "notEmptySlots": false,
                "address": {
                    "street": "ул. Ленина",
                    "house": "д. 87Б",
                    "fullAddress": "г. Ижевск, ул. Ленина, д. 87Б"
                },
                "cityId": 0,
                "diagnosticsName": null,
                "diagnosticsPrice": null,
                "stations": null,
                "hasYandexCashBack": false,
                "receptionPrices": {
                    "clinic": {
                        "price": null,
                        "specialPrice": null
                    }
                },
                "isPriorityPartner": false,
                "adultsReception": 1,
                "kidsReception": 0,
                "kidsReceptionAgeRange": []
            }
        },
        "slots": [],
        "categoryId": 2,
        "categoryTitle": "Врач первой категории",
        "experience": 16,
        "degreeId": 0,
        "degreeAbbreviation": "",
        "degreeTitle": "",
        "hasPromoPrice": false,
        "hasStandardPrice": false,
        "hasYandexCashBack": false,
        "departurePrice": null,
        "tooltipText": "Стоимость указана за первичный приём.\nВ неё не входит стоимость дополнительных исследований и выезда на дом.",
        "seoSlotTipText": "",
        "isEnabledPromoPrice": false,
        "review": [],
        "specAccommodationIndex": null,
        "surgeryInfo": null
    },
    {
        "id": 581528,
        "isActive": false,
        "isHidden": true,
        "isFavorite": false,
        "name": "Мартынова Татьяна Александровна",
        "surname": "",
        "alias": "Martynova_Tatyana_5",
        "sex": 2,
        "url": "/doctor/Martynova_Tatyana_5",
        "logo": null,
        "rectangularImage": null,
        "image": "",
        "mobileImage": "",
        "tipMessage": "",
        "departure": false,
        "kidsReception": false,
        "rating": {
            "label": "Очень хороший",
            "rating": 0,
            "doctorRating": 8.2
        },
        "popularityRating": 0,
        "doctorExt": false,
        "index": 4,
        "ratingType": "stars_and_label",
        "countReviewsString": "0 отзывов",
        "countReviews": 0,
        "topReviewsPercent": 0,
        "rank": null,
        "specialities": [
            {
                "id": 75,
                "name": "Кардиолог",
                "alias": "kardiolog"
            }
        ],
        "tooltipPrices": [
            {
                "clinicAddress": "г. Ижевск, ул. Ленина, д. 87Б",
                "price": null,
                "specialPrice": null,
                "sectorNames": "Кардиолог"
            }
        ],
        "standardPrices": [],
        "highlight": 0,
        "clinics": {
            "93516": {
                "active": true,
                "selected": true,
                "id": 93516,
                "name": "Республиканский клинико-диагностический центр Министерства Здравоохранения Удмуртской Республики",
                "alias": "respublikanskiy_kliniko-diagnosticheskiy_tsentr_ministerstva_zdravoohraneniya_udmurtskoy_respubliki",
                "url": "/clinic/respublikanskiy_kliniko-diagnosticheskiy_tsentr_ministerstva_zdravoohraneniya_udmurtskoy_respubliki",
                "phone": "8 (495) 125-29-52",
                "price": null,
                "specialPrice": null,
                "coords": [
                    56.849118,
                    53.251429
                ],
                "isPrivateDoctor": false,
                "isRecommended": false,
                "notEmptySlots": false,
                "address": {
                    "street": "ул. Ленина",
                    "house": "д. 87Б",
                    "fullAddress": "г. Ижевск, ул. Ленина, д. 87Б"
                },
                "cityId": 0,
                "diagnosticsName": null,
                "diagnosticsPrice": null,
                "stations": null,
                "hasYandexCashBack": false,
                "receptionPrices": {
                    "clinic": {
                        "price": null,
                        "specialPrice": null
                    }
                },
                "isPriorityPartner": false,
                "adultsReception": 1,
                "kidsReception": 0,
                "kidsReceptionAgeRange": []
            }
        },
        "slots": [],
        "categoryId": 2,
        "categoryTitle": "Врач первой категории",
        "experience": 15,
        "degreeId": 0,
        "degreeAbbreviation": "",
        "degreeTitle": "",
        "hasPromoPrice": false,
        "hasStandardPrice": false,
        "hasYandexCashBack": false,
        "departurePrice": null,
        "tooltipText": "Стоимость указана за первичный приём.\nВ неё не входит стоимость дополнительных исследований и выезда на дом.",
        "seoSlotTipText": "",
        "isEnabledPromoPrice": false,
        "review": [],
        "specAccommodationIndex": null,
        "surgeryInfo": null
    },
    {
        "id": 581556,
        "isActive": false,
        "isHidden": true,
        "isFavorite": false,
        "name": "Королёв Иван Владимирович",
        "surname": "",
        "alias": "Korolyov_Ivan",
        "sex": 1,
        "url": "/doctor/Korolyov_Ivan",
        "logo": null,
        "rectangularImage": null,
        "image": "",
        "mobileImage": "",
        "tipMessage": "",
        "departure": false,
        "kidsReception": false,
        "rating": {
            "label": "Очень хороший",
            "rating": 0,
            "doctorRating": 8.2
        },
        "popularityRating": 0,
        "doctorExt": false,
        "index": 5,
        "ratingType": "stars_and_label",
        "countReviewsString": "0 отзывов",
        "countReviews": 0,
        "topReviewsPercent": 0,
        "rank": null,
        "specialities": [
            {
                "id": 107,
                "name": "Анестезиолог",
                "alias": "anesteziolog"
            },
            {
                "id": 204,
                "name": "Реаниматолог",
                "alias": "reanimatolog"
            }
        ],
        "tooltipPrices": [
            {
                "clinicAddress": "г. Ижевск, ул. Ленина, д. 87Б",
                "price": null,
                "specialPrice": null,
                "sectorNames": "Анестезиолог, Реаниматолог"
            }
        ],
        "standardPrices": [],
        "highlight": 0,
        "clinics": {
            "93516": {
                "active": true,
                "selected": true,
                "id": 93516,
                "name": "Республиканский клинико-диагностический центр Министерства Здравоохранения Удмуртской Республики",
                "alias": "respublikanskiy_kliniko-diagnosticheskiy_tsentr_ministerstva_zdravoohraneniya_udmurtskoy_respubliki",
                "url": "/clinic/respublikanskiy_kliniko-diagnosticheskiy_tsentr_ministerstva_zdravoohraneniya_udmurtskoy_respubliki",
                "phone": "8 (495) 125-29-52",
                "price": null,
                "specialPrice": null,
                "coords": [
                    56.849118,
                    53.251429
                ],
                "isPrivateDoctor": false,
                "isRecommended": false,
                "notEmptySlots": false,
                "address": {
                    "street": "ул. Ленина",
                    "house": "д. 87Б",
                    "fullAddress": "г. Ижевск, ул. Ленина, д. 87Б"
                },
                "cityId": 0,
                "diagnosticsName": null,
                "diagnosticsPrice": null,
                "stations": null,
                "hasYandexCashBack": false,
                "receptionPrices": {
                    "clinic": {
                        "price": null,
                        "specialPrice": null
                    }
                },
                "isPriorityPartner": false,
                "adultsReception": 1,
                "kidsReception": 0,
                "kidsReceptionAgeRange": []
            }
        },
        "slots": [],
        "categoryId": 2,
        "categoryTitle": "Врач первой категории",
        "experience": 14,
        "degreeId": 0,
        "degreeAbbreviation": "",
        "degreeTitle": "",
        "hasPromoPrice": false,
        "hasStandardPrice": false,
        "hasYandexCashBack": false,
        "departurePrice": null,
        "tooltipText": "Стоимость указана за первичный приём.\nВ неё не входит стоимость дополнительных исследований и выезда на дом.",
        "seoSlotTipText": "",
        "isEnabledPromoPrice": false,
        "review": [],
        "specAccommodationIndex": null,
        "surgeryInfo": null
    },
    {
        "id": 581566,
        "isActive": false,
        "isHidden": true,
        "isFavorite": false,
        "name": "Ризванова Раушания Талгатовна",
        "surname": "",
        "alias": "Rizvanova_Raushaniya",
        "sex": 2,
        "url": "/doctor/Rizvanova_Raushaniya",
        "logo": null,
        "rectangularImage": null,
        "image": "",
        "mobileImage": "",
        "tipMessage": "",
        "departure": false,
        "kidsReception": false,
        "rating": {
            "label": "Очень хороший",
            "rating": 0,
            "doctorRating": 8
        },
        "popularityRating": 0,
        "doctorExt": false,
        "index": 6,
        "ratingType": "stars_and_label",
        "countReviewsString": "0 отзывов",
        "countReviews": 0,
        "topReviewsPercent": 0,
        "rank": null,
        "specialities": [
            {
                "id": 75,
                "name": "Кардиолог",
                "alias": "kardiolog"
            }
        ],
        "tooltipPrices": [
            {
                "clinicAddress": "г. Ижевск, ул. Ленина, д. 87Б",
                "price": null,
                "specialPrice": null,
                "sectorNames": "Кардиолог"
            }
        ],
        "standardPrices": [],
        "highlight": 0,
        "clinics": {
            "93516": {
                "active": true,
                "selected": true,
                "id": 93516,
                "name": "Республиканский клинико-диагностический центр Министерства Здравоохранения Удмуртской Республики",
                "alias": "respublikanskiy_kliniko-diagnosticheskiy_tsentr_ministerstva_zdravoohraneniya_udmurtskoy_respubliki",
                "url": "/clinic/respublikanskiy_kliniko-diagnosticheskiy_tsentr_ministerstva_zdravoohraneniya_udmurtskoy_respubliki",
                "phone": "8 (495) 125-29-52",
                "price": null,
                "specialPrice": null,
                "coords": [
                    56.849118,
                    53.251429
                ],
                "isPrivateDoctor": false,
                "isRecommended": false,
                "notEmptySlots": false,
                "address": {
                    "street": "ул. Ленина",
                    "house": "д. 87Б",
                    "fullAddress": "г. Ижевск, ул. Ленина, д. 87Б"
                },
                "cityId": 0,
                "diagnosticsName": null,
                "diagnosticsPrice": null,
                "stations": null,
                "hasYandexCashBack": false,
                "receptionPrices": {
                    "clinic": {
                        "price": null,
                        "specialPrice": null
                    }
                },
                "isPriorityPartner": false,
                "adultsReception": 1,
                "kidsReception": 0,
                "kidsReceptionAgeRange": []
            }
        },
        "slots": [],
        "categoryId": 3,
        "categoryTitle": "Врач второй категории",
        "experience": 14,
        "degreeId": 1,
        "degreeAbbreviation": "к.м.н.",
        "degreeTitle": "Кандидат медицинских наук",
        "hasPromoPrice": false,
        "hasStandardPrice": false,
        "hasYandexCashBack": false,
        "departurePrice": null,
        "tooltipText": "Стоимость указана за первичный приём.\nВ неё не входит стоимость дополнительных исследований и выезда на дом.",
        "seoSlotTipText": "",
        "isEnabledPromoPrice": false,
        "review": [],
        "specAccommodationIndex": null,
        "surgeryInfo": null
    },
    {
        "id": 581578,
        "isActive": false,
        "isHidden": true,
        "isFavorite": false,
        "name": "Сухих Михаил Николаевич",
        "surname": "",
        "alias": "Suhih_Mihail",
        "sex": 1,
        "url": "/doctor/Suhih_Mihail",
        "logo": null,
        "rectangularImage": null,
        "image": "",
        "mobileImage": "",
        "tipMessage": "",
        "departure": false,
        "kidsReception": false,
        "rating": {
            "label": "Очень хороший",
            "rating": 0,
            "doctorRating": 8.2
        },
        "popularityRating": 0,
        "doctorExt": false,
        "index": 7,
        "ratingType": "stars_and_label",
        "countReviewsString": "0 отзывов",
        "countReviews": 0,
        "topReviewsPercent": 0,
        "rank": null,
        "specialities": [
            {
                "id": 107,
                "name": "Анестезиолог",
                "alias": "anesteziolog"
            },
            {
                "id": 250,
                "name": "Анестезиолог-реаниматолог",
                "alias": "anesteziolog-reanimatolog"
            },
            {
                "id": 204,
                "name": "Реаниматолог",
                "alias": "reanimatolog"
            }
        ],
        "tooltipPrices": [
            {
                "clinicAddress": "г. Ижевск, ул. Ленина, д. 87Б",
                "price": null,
                "specialPrice": null,
                "sectorNames": "Анестезиолог, Реаниматолог, Анестезиолог-реаниматолог"
            }
        ],
        "standardPrices": [],
        "highlight": 0,
        "clinics": {
            "93516": {
                "active": true,
                "selected": true,
                "id": 93516,
                "name": "Республиканский клинико-диагностический центр Министерства Здравоохранения Удмуртской Республики",
                "alias": "respublikanskiy_kliniko-diagnosticheskiy_tsentr_ministerstva_zdravoohraneniya_udmurtskoy_respubliki",
                "url": "/clinic/respublikanskiy_kliniko-diagnosticheskiy_tsentr_ministerstva_zdravoohraneniya_udmurtskoy_respubliki",
                "phone": "8 (495) 125-29-52",
                "price": null,
                "specialPrice": null,
                "coords": [
                    56.849118,
                    53.251429
                ],
                "isPrivateDoctor": false,
                "isRecommended": false,
                "notEmptySlots": false,
                "address": {
                    "street": "ул. Ленина",
                    "house": "д. 87Б",
                    "fullAddress": "г. Ижевск, ул. Ленина, д. 87Б"
                },
                "cityId": 0,
                "diagnosticsName": null,
                "diagnosticsPrice": null,
                "stations": null,
                "hasYandexCashBack": false,
                "receptionPrices": {
                    "clinic": {
                        "price": null,
                        "specialPrice": null
                    }
                },
                "isPriorityPartner": false,
                "adultsReception": 1,
                "kidsReception": 0,
                "kidsReceptionAgeRange": []
            }
        },
        "slots": [],
        "categoryId": 2,
        "categoryTitle": "Врач первой категории",
        "experience": 13,
        "degreeId": 0,
        "degreeAbbreviation": "",
        "degreeTitle": "",
        "hasPromoPrice": false,
        "hasStandardPrice": false,
        "hasYandexCashBack": false,
        "departurePrice": null,
        "tooltipText": "Стоимость указана за первичный приём.\nВ неё не входит стоимость дополнительных исследований и выезда на дом.",
        "seoSlotTipText": "",
        "isEnabledPromoPrice": false,
        "review": [],
        "specAccommodationIndex": null,
        "surgeryInfo": null
    },
    {
        "id": 581594,
        "isActive": false,
        "isHidden": true,
        "isFavorite": false,
        "name": "Пульгребяк Елена Юрьевна",
        "surname": "",
        "alias": "Pulgrebyak_Elena",
        "sex": 2,
        "url": "/doctor/Pulgrebyak_Elena",
        "logo": null,
        "rectangularImage": null,
        "image": "",
        "mobileImage": "",
        "tipMessage": "",
        "departure": false,
        "kidsReception": false,
        "rating": {
            "label": "Очень хороший",
            "rating": 0,
            "doctorRating": 8.6
        },
        "popularityRating": 0,
        "doctorExt": false,
        "index": 8,
        "ratingType": "stars_and_label",
        "countReviewsString": "0 отзывов",
        "countReviews": 0,
        "topReviewsPercent": 0,
        "rank": null,
        "specialities": [
            {
                "id": 75,
                "name": "Кардиолог",
                "alias": "kardiolog"
            }
        ],
        "tooltipPrices": [
            {
                "clinicAddress": "г. Ижевск, ул. Ленина, д. 87Б",
                "price": null,
                "specialPrice": null,
                "sectorNames": "Кардиолог"
            }
        ],
        "standardPrices": [],
        "highlight": 0,
        "clinics": {
            "93516": {
                "active": true,
                "selected": true,
                "id": 93516,
                "name": "Республиканский клинико-диагностический центр Министерства Здравоохранения Удмуртской Республики",
                "alias": "respublikanskiy_kliniko-diagnosticheskiy_tsentr_ministerstva_zdravoohraneniya_udmurtskoy_respubliki",
                "url": "/clinic/respublikanskiy_kliniko-diagnosticheskiy_tsentr_ministerstva_zdravoohraneniya_udmurtskoy_respubliki",
                "phone": "8 (495) 125-29-52",
                "price": null,
                "specialPrice": null,
                "coords": [
                    56.849118,
                    53.251429
                ],
                "isPrivateDoctor": false,
                "isRecommended": false,
                "notEmptySlots": false,
                "address": {
                    "street": "ул. Ленина",
                    "house": "д. 87Б",
                    "fullAddress": "г. Ижевск, ул. Ленина, д. 87Б"
                },
                "cityId": 0,
                "diagnosticsName": null,
                "diagnosticsPrice": null,
                "stations": null,
                "hasYandexCashBack": false,
                "receptionPrices": {
                    "clinic": {
                        "price": null,
                        "specialPrice": null
                    }
                },
                "isPriorityPartner": false,
                "adultsReception": 1,
                "kidsReception": 0,
                "kidsReceptionAgeRange": []
            }
        },
        "slots": [],
        "categoryId": 3,
        "categoryTitle": "Врач второй категории",
        "experience": 17,
        "degreeId": 0,
        "degreeAbbreviation": "",
        "degreeTitle": "",
        "hasPromoPrice": false,
        "hasStandardPrice": false,
        "hasYandexCashBack": false,
        "departurePrice": null,
        "tooltipText": "Стоимость указана за первичный приём.\nВ неё не входит стоимость дополнительных исследований и выезда на дом.",
        "seoSlotTipText": "",
        "isEnabledPromoPrice": false,
        "review": [],
        "specAccommodationIndex": null,
        "surgeryInfo": null
    },
    {
        "id": 581602,
        "isActive": false,
        "isHidden": true,
        "isFavorite": false,
        "name": "Богданов Алексей Владимирович",
        "surname": "",
        "alias": "Bogdanov_Aleksey_5",
        "sex": 1,
        "url": "/doctor/Bogdanov_Aleksey_5",
        "logo": null,
        "rectangularImage": null,
        "image": "",
        "mobileImage": "",
        "tipMessage": "",
        "departure": false,
        "kidsReception": false,
        "rating": {
            "label": "Очень хороший",
            "rating": 0,
            "doctorRating": 8.6
        },
        "popularityRating": 0,
        "doctorExt": false,
        "index": 9,
        "ratingType": "stars_and_label",
        "countReviewsString": "0 отзывов",
        "countReviews": 0,
        "topReviewsPercent": 0,
        "rank": null,
        "specialities": [
            {
                "id": 101,
                "name": "Массажист",
                "alias": "massazhist"
            }
        ],
        "tooltipPrices": [
            {
                "clinicAddress": "г. Ижевск, ул. Ленина, д. 87Б",
                "price": null,
                "specialPrice": null,
                "sectorNames": "Массажист"
            }
        ],
        "standardPrices": [],
        "highlight": 0,
        "clinics": {
            "93516": {
                "active": true,
                "selected": true,
                "id": 93516,
                "name": "Республиканский клинико-диагностический центр Министерства Здравоохранения Удмуртской Республики",
                "alias": "respublikanskiy_kliniko-diagnosticheskiy_tsentr_ministerstva_zdravoohraneniya_udmurtskoy_respubliki",
                "url": "/clinic/respublikanskiy_kliniko-diagnosticheskiy_tsentr_ministerstva_zdravoohraneniya_udmurtskoy_respubliki",
                "phone": "8 (495) 125-29-52",
                "price": null,
                "specialPrice": null,
                "coords": [
                    56.849118,
                    53.251429
                ],
                "isPrivateDoctor": false,
                "isRecommended": false,
                "notEmptySlots": false,
                "address": {
                    "street": "ул. Ленина",
                    "house": "д. 87Б",
                    "fullAddress": "г. Ижевск, ул. Ленина, д. 87Б"
                },
                "cityId": 0,
                "diagnosticsName": null,
                "diagnosticsPrice": null,
                "stations": null,
                "hasYandexCashBack": false,
                "receptionPrices": {
                    "clinic": {
                        "price": null,
                        "specialPrice": null
                    }
                },
                "isPriorityPartner": false,
                "adultsReception": 1,
                "kidsReception": 0,
                "kidsReceptionAgeRange": []
            }
        },
        "slots": [],
        "categoryId": 3,
        "categoryTitle": "Врач второй категории",
        "experience": 22,
        "degreeId": 0,
        "degreeAbbreviation": "",
        "degreeTitle": "",
        "hasPromoPrice": false,
        "hasStandardPrice": false,
        "hasYandexCashBack": false,
        "departurePrice": null,
        "tooltipText": "Стоимость указана за первичный приём.\nВ неё не входит стоимость дополнительных исследований и выезда на дом.",
        "seoSlotTipText": "",
        "isEnabledPromoPrice": false,
        "review": [],
        "specAccommodationIndex": null,
        "surgeryInfo": null
    }
]}