{"doctors": [
    {
        "id": 589736,
        "isActive": false,
        "isHidden": true,
        "isFavorite": false,
        "name": "Кислицына Ирина Анатольевна",
        "surname": "",
        "alias": "Kislitsyna_Irina_2",
        "sex": 2,
        "url": "/doctor/Kislitsyna_Irina_2",
        "logo": null,
        "rectangularImage": null,
        "image": "",
        "mobileImage": "",
        "tipMessage": "",
        "departure": false,
        "kidsReception": false,
        "rating": {
            "label": "Превосходный",
            "rating": 0,
            "doctorRating": 8.8
        },
        "popularityRating": 0,
        "doctorExt": false,
        "index": 0,
        "ratingType": "stars_and_label",
        "countReviewsString": "0 отзывов",
        "countReviews": 0,
        "topReviewsPercent": 0,
        "rank": null,
        "specialities": [
            {
                "id": 67,
                "name": "Акушер",
                "alias": "akusher"
            },
            {
                "id": 72,
                "name": "Гинеколог",
                "alias": "ginekolog"
            }
        ],
        "tooltipPrices": [
            {
                "clinicAddress": "г. Ижевск, ул. Серова, д. 65",
                "price": null,
                "specialPrice": null,
                "sectorNames": "Акушер, Гинеколог"
            }
        ],
        "standardPrices": [],
        "highlight": 0,
        "clinics": {
            "96886": {
                "active": true,
                "selected": true,
                "id": 96886,
                "name": "Больница №8 Однопозова",
                "alias": "bolnitsa_8_odnopozova",
                "url": "/clinic/bolnitsa_8_odnopozova",
                "phone": "8 (495) 125-29-52",
                "price": null,
                "specialPrice": null,
                "coords": [
                    56.869569,
                    53.239428
                ],
                "isPrivateDoctor": false,
                "isRecommended": false,
                "notEmptySlots": false,
                "address": {
                    "street": "ул. Серова",
                    "house": "д. 65",
                    "fullAddress": "г. Ижевск, ул. Серова, д. 65"
                },
                "cityId": 0,
                "diagnosticsName": null,
                "diagnosticsPrice": null,
                "stations": null,
                "hasYandexCashBack": false,
                "receptionPrices": {
                    "clinic": {
                        "price": null,
                        "specialPrice": null
                    }
                },
                "isPriorityPartner": false,
                "adultsReception": 1,
                "kidsReception": 0,
                "kidsReceptionAgeRange": []
            }
        },
        "slots": [],
        "categoryId": 1,
        "categoryTitle": "Врач высшей категории",
        "experience": 31,
        "degreeId": 0,
        "degreeAbbreviation": "",
        "degreeTitle": "",
        "hasPromoPrice": false,
        "hasStandardPrice": false,
        "hasYandexCashBack": false,
        "departurePrice": null,
        "tooltipText": "Стоимость указана за первичный приём.\nВ неё не входит стоимость дополнительных исследований и выезда на дом.",
        "seoSlotTipText": "",
        "isEnabledPromoPrice": false,
        "review": [],
        "specAccommodationIndex": null,
        "surgeryInfo": null
    },
    {
        "id": 589740,
        "isActive": false,
        "isHidden": true,
        "isFavorite": false,
        "name": "Бабушкин Игнатий Валерьевич",
        "surname": "",
        "alias": "Babushkin_Ignatiy",
        "sex": 1,
        "url": "/doctor/Babushkin_Ignatiy",
        "logo": null,
        "rectangularImage": null,
        "image": "",
        "mobileImage": "",
        "tipMessage": "",
        "departure": false,
        "kidsReception": false,
        "rating": {
            "label": "Очень хороший",
            "rating": 0,
            "doctorRating": 8.6
        },
        "popularityRating": 0,
        "doctorExt": false,
        "index": 1,
        "ratingType": "stars_and_label",
        "countReviewsString": "0 отзывов",
        "countReviews": 0,
        "topReviewsPercent": 0,
        "rank": null,
        "specialities": [
            {
                "id": 107,
                "name": "Анестезиолог",
                "alias": "anesteziolog"
            },
            {
                "id": 250,
                "name": "Анестезиолог-реаниматолог",
                "alias": "anesteziolog-reanimatolog"
            },
            {
                "id": 204,
                "name": "Реаниматолог",
                "alias": "reanimatolog"
            }
        ],
        "tooltipPrices": [
            {
                "clinicAddress": "г. Ижевск, ул. Серова, д. 65",
                "price": null,
                "specialPrice": null,
                "sectorNames": "Анестезиолог, Реаниматолог, Анестезиолог-реаниматолог"
            }
        ],
        "standardPrices": [],
        "highlight": 0,
        "clinics": {
            "96886": {
                "active": true,
                "selected": true,
                "id": 96886,
                "name": "Больница №8 Однопозова",
                "alias": "bolnitsa_8_odnopozova",
                "url": "/clinic/bolnitsa_8_odnopozova",
                "phone": "8 (495) 125-29-52",
                "price": null,
                "specialPrice": null,
                "coords": [
                    56.869569,
                    53.239428
                ],
                "isPrivateDoctor": false,
                "isRecommended": false,
                "notEmptySlots": false,
                "address": {
                    "street": "ул. Серова",
                    "house": "д. 65",
                    "fullAddress": "г. Ижевск, ул. Серова, д. 65"
                },
                "cityId": 0,
                "diagnosticsName": null,
                "diagnosticsPrice": null,
                "stations": null,
                "hasYandexCashBack": false,
                "receptionPrices": {
                    "clinic": {
                        "price": null,
                        "specialPrice": null
                    }
                },
                "isPriorityPartner": false,
                "adultsReception": 1,
                "kidsReception": 0,
                "kidsReceptionAgeRange": []
            }
        },
        "slots": [],
        "categoryId": 0,
        "categoryTitle": "",
        "experience": 16,
        "degreeId": 0,
        "degreeAbbreviation": "",
        "degreeTitle": "",
        "hasPromoPrice": false,
        "hasStandardPrice": false,
        "hasYandexCashBack": false,
        "departurePrice": null,
        "tooltipText": "Стоимость указана за первичный приём.\nВ неё не входит стоимость дополнительных исследований и выезда на дом.",
        "seoSlotTipText": "",
        "isEnabledPromoPrice": false,
        "review": [],
        "specAccommodationIndex": null,
        "surgeryInfo": null
    },
    {
        "id": 589746,
        "isActive": false,
        "isHidden": true,
        "isFavorite": false,
        "name": "Киреева Наталья Владимировна",
        "surname": "",
        "alias": "Kireeva_Natalya_9",
        "sex": 2,
        "url": "/doctor/Kireeva_Natalya_9",
        "logo": null,
        "rectangularImage": null,
        "image": "https://cdn.docdoc.ru/doctor/589746_20201123001220.162x162.jpg?1669431298",
        "mobileImage": "https://cdn.docdoc.ru/doctor/589746_20201123001220.640x400.jpg?1669431298",
        "tipMessage": "",
        "departure": false,
        "kidsReception": false,
        "rating": {
            "label": "Очень хороший",
            "rating": 0,
            "doctorRating": 8.6
        },
        "popularityRating": 0,
        "doctorExt": false,
        "index": 2,
        "ratingType": "stars_and_label",
        "countReviewsString": "0 отзывов",
        "countReviews": 0,
        "topReviewsPercent": 0,
        "rank": null,
        "specialities": [
            {
                "id": 133,
                "name": "Эндоскопист",
                "alias": "endoskopist"
            }
        ],
        "tooltipPrices": [
            {
                "clinicAddress": "г. Ижевск, ул. Серова, д. 65",
                "price": null,
                "specialPrice": null,
                "sectorNames": "Эндоскопист"
            }
        ],
        "standardPrices": [],
        "highlight": 0,
        "clinics": {
            "96886": {
                "active": true,
                "selected": true,
                "id": 96886,
                "name": "Больница №8 Однопозова",
                "alias": "bolnitsa_8_odnopozova",
                "url": "/clinic/bolnitsa_8_odnopozova",
                "phone": "8 (495) 125-29-52",
                "price": null,
                "specialPrice": null,
                "coords": [
                    56.869569,
                    53.239428
                ],
                "isPrivateDoctor": false,
                "isRecommended": false,
                "notEmptySlots": false,
                "address": {
                    "street": "ул. Серова",
                    "house": "д. 65",
                    "fullAddress": "г. Ижевск, ул. Серова, д. 65"
                },
                "cityId": 0,
                "diagnosticsName": null,
                "diagnosticsPrice": null,
                "stations": null,
                "hasYandexCashBack": false,
                "receptionPrices": {
                    "clinic": {
                        "price": null,
                        "specialPrice": null
                    }
                },
                "isPriorityPartner": false,
                "adultsReception": 1,
                "kidsReception": 0,
                "kidsReceptionAgeRange": []
            }
        },
        "slots": [],
        "categoryId": 2,
        "categoryTitle": "Врач первой категории",
        "experience": 23,
        "degreeId": 0,
        "degreeAbbreviation": "",
        "degreeTitle": "",
        "hasPromoPrice": false,
        "hasStandardPrice": false,
        "hasYandexCashBack": false,
        "departurePrice": null,
        "tooltipText": "Стоимость указана за первичный приём.\nВ неё не входит стоимость дополнительных исследований и выезда на дом.",
        "seoSlotTipText": "",
        "isEnabledPromoPrice": false,
        "review": [],
        "specAccommodationIndex": null,
        "surgeryInfo": null
    },
    {
        "id": 589748,
        "isActive": false,
        "isHidden": true,
        "isFavorite": false,
        "name": "Михайлова Ольга Дмитриевна",
        "surname": "",
        "alias": "Mihaylova_Olga_24",
        "sex": 2,
        "url": "/doctor/Mihaylova_Olga_24",
        "logo": null,
        "rectangularImage": null,
        "image": "",
        "mobileImage": "",
        "tipMessage": "",
        "departure": false,
        "kidsReception": false,
        "rating": {
            "label": "Очень хороший",
            "rating": 0,
            "doctorRating": 8.6
        },
        "popularityRating": 0,
        "doctorExt": false,
        "index": 3,
        "ratingType": "stars_and_label",
        "countReviewsString": "0 отзывов",
        "countReviews": 0,
        "topReviewsPercent": 0,
        "rank": null,
        "specialities": [
            {
                "id": 91,
                "name": "Терапевт",
                "alias": "terapevt"
            }
        ],
        "tooltipPrices": [
            {
                "clinicAddress": "г. Ижевск, ул. Серова, д. 65",
                "price": null,
                "specialPrice": null,
                "sectorNames": "Терапевт"
            }
        ],
        "standardPrices": [],
        "highlight": 0,
        "clinics": {
            "96886": {
                "active": true,
                "selected": true,
                "id": 96886,
                "name": "Больница №8 Однопозова",
                "alias": "bolnitsa_8_odnopozova",
                "url": "/clinic/bolnitsa_8_odnopozova",
                "phone": "8 (495) 125-29-52",
                "price": null,
                "specialPrice": null,
                "coords": [
                    56.869569,
                    53.239428
                ],
                "isPrivateDoctor": false,
                "isRecommended": false,
                "notEmptySlots": false,
                "address": {
                    "street": "ул. Серова",
                    "house": "д. 65",
                    "fullAddress": "г. Ижевск, ул. Серова, д. 65"
                },
                "cityId": 0,
                "diagnosticsName": null,
                "diagnosticsPrice": null,
                "stations": null,
                "hasYandexCashBack": false,
                "receptionPrices": {
                    "clinic": {
                        "price": null,
                        "specialPrice": null
                    }
                },
                "isPriorityPartner": false,
                "adultsReception": 1,
                "kidsReception": 0,
                "kidsReceptionAgeRange": []
            }
        },
        "slots": [],
        "categoryId": 1,
        "categoryTitle": "Врач высшей категории",
        "experience": 27,
        "degreeId": 0,
        "degreeAbbreviation": "",
        "degreeTitle": "",
        "hasPromoPrice": false,
        "hasStandardPrice": false,
        "hasYandexCashBack": false,
        "departurePrice": null,
        "tooltipText": "Стоимость указана за первичный приём.\nВ неё не входит стоимость дополнительных исследований и выезда на дом.",
        "seoSlotTipText": "",
        "isEnabledPromoPrice": false,
        "review": [],
        "specAccommodationIndex": null,
        "surgeryInfo": null
    },
    {
        "id": 589750,
        "isActive": false,
        "isHidden": true,
        "isFavorite": false,
        "name": "Агеев Денис Павлович",
        "surname": "",
        "alias": "Ageev_Denis",
        "sex": 1,
        "url": "/doctor/Ageev_Denis",
        "logo": null,
        "rectangularImage": null,
        "image": "",
        "mobileImage": "",
        "tipMessage": "",
        "departure": false,
        "kidsReception": false,
        "rating": {
            "label": "Очень хороший",
            "rating": 0,
            "doctorRating": 8.6
        },
        "popularityRating": 0,
        "doctorExt": false,
        "index": 4,
        "ratingType": "stars_and_label",
        "countReviewsString": "0 отзывов",
        "countReviews": 0,
        "topReviewsPercent": 0,
        "rank": null,
        "specialities": [
            {
                "id": 107,
                "name": "Анестезиолог",
                "alias": "anesteziolog"
            },
            {
                "id": 250,
                "name": "Анестезиолог-реаниматолог",
                "alias": "anesteziolog-reanimatolog"
            },
            {
                "id": 204,
                "name": "Реаниматолог",
                "alias": "reanimatolog"
            }
        ],
        "tooltipPrices": [
            {
                "clinicAddress": "г. Ижевск, ул. Серова, д. 65",
                "price": null,
                "specialPrice": null,
                "sectorNames": "Анестезиолог, Реаниматолог, Анестезиолог-реаниматолог"
            }
        ],
        "standardPrices": [],
        "highlight": 0,
        "clinics": {
            "96886": {
                "active": true,
                "selected": true,
                "id": 96886,
                "name": "Больница №8 Однопозова",
                "alias": "bolnitsa_8_odnopozova",
                "url": "/clinic/bolnitsa_8_odnopozova",
                "phone": "8 (495) 125-29-52",
                "price": null,
                "specialPrice": null,
                "coords": [
                    56.869569,
                    53.239428
                ],
                "isPrivateDoctor": false,
                "isRecommended": false,
                "notEmptySlots": false,
                "address": {
                    "street": "ул. Серова",
                    "house": "д. 65",
                    "fullAddress": "г. Ижевск, ул. Серова, д. 65"
                },
                "cityId": 0,
                "diagnosticsName": null,
                "diagnosticsPrice": null,
                "stations": null,
                "hasYandexCashBack": false,
                "receptionPrices": {
                    "clinic": {
                        "price": null,
                        "specialPrice": null
                    }
                },
                "isPriorityPartner": false,
                "adultsReception": 1,
                "kidsReception": 0,
                "kidsReceptionAgeRange": []
            }
        },
        "slots": [],
        "categoryId": 1,
        "categoryTitle": "Врач высшей категории",
        "experience": 24,
        "degreeId": 0,
        "degreeAbbreviation": "",
        "degreeTitle": "",
        "hasPromoPrice": false,
        "hasStandardPrice": false,
        "hasYandexCashBack": false,
        "departurePrice": null,
        "tooltipText": "Стоимость указана за первичный приём.\nВ неё не входит стоимость дополнительных исследований и выезда на дом.",
        "seoSlotTipText": "",
        "isEnabledPromoPrice": false,
        "review": [],
        "specAccommodationIndex": null,
        "surgeryInfo": null
    },
    {
        "id": 589752,
        "isActive": false,
        "isHidden": true,
        "isFavorite": false,
        "name": "Моргунов Сергей Сергеевич",
        "surname": "",
        "alias": "Morgunov_Sergey_2",
        "sex": 1,
        "url": "/doctor/Morgunov_Sergey_2",
        "logo": null,
        "rectangularImage": null,
        "image": "",
        "mobileImage": "",
        "tipMessage": "",
        "departure": false,
        "kidsReception": false,
        "rating": {
            "label": "Превосходный",
            "rating": 0,
            "doctorRating": 8.8
        },
        "popularityRating": 0,
        "doctorExt": false,
        "index": 5,
        "ratingType": "stars_and_label",
        "countReviewsString": "0 отзывов",
        "countReviews": 0,
        "topReviewsPercent": 0,
        "rank": null,
        "specialities": [
            {
                "id": 107,
                "name": "Анестезиолог",
                "alias": "anesteziolog"
            },
            {
                "id": 250,
                "name": "Анестезиолог-реаниматолог",
                "alias": "anesteziolog-reanimatolog"
            },
            {
                "id": 204,
                "name": "Реаниматолог",
                "alias": "reanimatolog"
            }
        ],
        "tooltipPrices": [
            {
                "clinicAddress": "г. Ижевск, ул. Серова, д. 65",
                "price": null,
                "specialPrice": null,
                "sectorNames": "Анестезиолог, Реаниматолог, Анестезиолог-реаниматолог"
            },
            {
                "clinicAddress": "г. Ижевск, ул. Пушкинская, д. 219",
                "price": null,
                "specialPrice": null,
                "sectorNames": "Анестезиолог, Реаниматолог, Анестезиолог-реаниматолог"
            }
        ],
        "standardPrices": [],
        "highlight": 0,
        "clinics": {
            "96886": {
                "active": true,
                "selected": true,
                "id": 96886,
                "name": "Больница №8 Однопозова",
                "alias": "bolnitsa_8_odnopozova",
                "url": "/clinic/bolnitsa_8_odnopozova",
                "phone": "8 (495) 125-29-52",
                "price": null,
                "specialPrice": null,
                "coords": [
                    56.869569,
                    53.239428
                ],
                "isPrivateDoctor": false,
                "isRecommended": false,
                "notEmptySlots": false,
                "address": {
                    "street": "ул. Серова",
                    "house": "д. 65",
                    "fullAddress": "г. Ижевск, ул. Серова, д. 65"
                },
                "cityId": 0,
                "diagnosticsName": null,
                "diagnosticsPrice": null,
                "stations": null,
                "hasYandexCashBack": false,
                "receptionPrices": {
                    "clinic": {
                        "price": null,
                        "specialPrice": null
                    }
                },
                "isPriorityPartner": false,
                "adultsReception": 1,
                "kidsReception": 0,
                "kidsReceptionAgeRange": []
            },
            "97680": {
                "active": false,
                "selected": false,
                "id": 97680,
                "name": "Городская клиническая больница № 2",
                "alias": "gorodskaya_klinicheskaya_bolnitsa_2_2",
                "url": "/clinic/gorodskaya_klinicheskaya_bolnitsa_2_2",
                "phone": "8 (495) 125-29-52",
                "price": null,
                "specialPrice": null,
                "coords": [
                    56.850905,
                    53.211715
                ],
                "isPrivateDoctor": false,
                "isRecommended": false,
                "notEmptySlots": false,
                "address": {
                    "street": "ул. Пушкинская",
                    "house": "д. 219",
                    "fullAddress": "г. Ижевск, ул. Пушкинская, д. 219"
                },
                "cityId": 0,
                "diagnosticsName": null,
                "diagnosticsPrice": null,
                "stations": null,
                "hasYandexCashBack": false,
                "receptionPrices": {
                    "clinic": {
                        "price": null,
                        "specialPrice": null
                    }
                },
                "isPriorityPartner": false,
                "adultsReception": 1,
                "kidsReception": 0,
                "kidsReceptionAgeRange": []
            }
        },
        "slots": [],
        "categoryId": 1,
        "categoryTitle": "Врач высшей категории",
        "experience": 33,
        "degreeId": 0,
        "degreeAbbreviation": "",
        "degreeTitle": "",
        "hasPromoPrice": false,
        "hasStandardPrice": false,
        "hasYandexCashBack": false,
        "departurePrice": null,
        "tooltipText": "Стоимость указана за первичный приём.\nВ неё не входит стоимость дополнительных исследований и выезда на дом.",
        "seoSlotTipText": "",
        "isEnabledPromoPrice": false,
        "review": [],
        "specAccommodationIndex": null,
        "surgeryInfo": null
    },
    {
        "id": 589754,
        "isActive": false,
        "isHidden": true,
        "isFavorite": false,
        "name": "Дмитриева Татьяна Юрьевна",
        "surname": "",
        "alias": "Dmitrieva_Tatyana_11",
        "sex": 2,
        "url": "/doctor/Dmitrieva_Tatyana_11",
        "logo": null,
        "rectangularImage": null,
        "image": "",
        "mobileImage": "",
        "tipMessage": "",
        "departure": false,
        "kidsReception": false,
        "rating": {
            "label": "Очень хороший",
            "rating": 0,
            "doctorRating": 8.6
        },
        "popularityRating": 0,
        "doctorExt": false,
        "index": 6,
        "ratingType": "stars_and_label",
        "countReviewsString": "0 отзывов",
        "countReviews": 0,
        "topReviewsPercent": 0,
        "rank": null,
        "specialities": [
            {
                "id": 71,
                "name": "Гастроэнтеролог",
                "alias": "gastroenterolog"
            }
        ],
        "tooltipPrices": [
            {
                "clinicAddress": "г. Ижевск, ул. Серова, д. 65",
                "price": null,
                "specialPrice": null,
                "sectorNames": "Гастроэнтеролог"
            }
        ],
        "standardPrices": [],
        "highlight": 0,
        "clinics": {
            "96886": {
                "active": true,
                "selected": true,
                "id": 96886,
                "name": "Больница №8 Однопозова",
                "alias": "bolnitsa_8_odnopozova",
                "url": "/clinic/bolnitsa_8_odnopozova",
                "phone": "8 (495) 125-29-52",
                "price": null,
                "specialPrice": null,
                "coords": [
                    56.869569,
                    53.239428
                ],
                "isPrivateDoctor": false,
                "isRecommended": false,
                "notEmptySlots": false,
                "address": {
                    "street": "ул. Серова",
                    "house": "д. 65",
                    "fullAddress": "г. Ижевск, ул. Серова, д. 65"
                },
                "cityId": 0,
                "diagnosticsName": null,
                "diagnosticsPrice": null,
                "stations": null,
                "hasYandexCashBack": false,
                "receptionPrices": {
                    "clinic": {
                        "price": null,
                        "specialPrice": null
                    }
                },
                "isPriorityPartner": false,
                "adultsReception": 1,
                "kidsReception": 0,
                "kidsReceptionAgeRange": []
            }
        },
        "slots": [],
        "categoryId": 1,
        "categoryTitle": "Врач высшей категории",
        "experience": 46,
        "degreeId": 0,
        "degreeAbbreviation": "",
        "degreeTitle": "",
        "hasPromoPrice": false,
        "hasStandardPrice": false,
        "hasYandexCashBack": false,
        "departurePrice": null,
        "tooltipText": "Стоимость указана за первичный приём.\nВ неё не входит стоимость дополнительных исследований и выезда на дом.",
        "seoSlotTipText": "",
        "isEnabledPromoPrice": false,
        "review": [],
        "specAccommodationIndex": null,
        "surgeryInfo": null
    },
    {
        "id": 589756,
        "isActive": false,
        "isHidden": true,
        "isFavorite": false,
        "name": "Логвиненко Лариса Георгиевна",
        "surname": "",
        "alias": "Logvinenko_Larisa",
        "sex": 2,
        "url": "/doctor/Logvinenko_Larisa",
        "logo": null,
        "rectangularImage": null,
        "image": "https://cdn.docdoc.ru/doctor/589756_20201123002720.162x162.jpg?1669431298",
        "mobileImage": "https://cdn.docdoc.ru/doctor/589756_20201123002720.640x400.jpg?1669431298",
        "tipMessage": "",
        "departure": false,
        "kidsReception": false,
        "rating": {
            "label": "Очень хороший",
            "rating": 0,
            "doctorRating": 8.6
        },
        "popularityRating": 0,
        "doctorExt": false,
        "index": 7,
        "ratingType": "stars_and_label",
        "countReviewsString": "0 отзывов",
        "countReviews": 0,
        "topReviewsPercent": 0,
        "rank": null,
        "specialities": [
            {
                "id": 72,
                "name": "Гинеколог",
                "alias": "ginekolog"
            },
            {
                "id": 100,
                "name": "УЗИ-специалист",
                "alias": "vrach_uzi"
            }
        ],
        "tooltipPrices": [
            {
                "clinicAddress": "г. Ижевск, ул. Серова, д. 65",
                "price": null,
                "specialPrice": null,
                "sectorNames": "Гинеколог, УЗИ-специалист"
            }
        ],
        "standardPrices": [],
        "highlight": 0,
        "clinics": {
            "96886": {
                "active": true,
                "selected": true,
                "id": 96886,
                "name": "Больница №8 Однопозова",
                "alias": "bolnitsa_8_odnopozova",
                "url": "/clinic/bolnitsa_8_odnopozova",
                "phone": "8 (495) 125-29-52",
                "price": null,
                "specialPrice": null,
                "coords": [
                    56.869569,
                    53.239428
                ],
                "isPrivateDoctor": false,
                "isRecommended": false,
                "notEmptySlots": false,
                "address": {
                    "street": "ул. Серова",
                    "house": "д. 65",
                    "fullAddress": "г. Ижевск, ул. Серова, д. 65"
                },
                "cityId": 0,
                "diagnosticsName": null,
                "diagnosticsPrice": null,
                "stations": null,
                "hasYandexCashBack": false,
                "receptionPrices": {
                    "clinic": {
                        "price": null,
                        "specialPrice": null
                    }
                },
                "isPriorityPartner": false,
                "adultsReception": 1,
                "kidsReception": 0,
                "kidsReceptionAgeRange": []
            }
        },
        "slots": [],
        "categoryId": 2,
        "categoryTitle": "Врач первой категории",
        "experience": 27,
        "degreeId": 0,
        "degreeAbbreviation": "",
        "degreeTitle": "",
        "hasPromoPrice": false,
        "hasStandardPrice": false,
        "hasYandexCashBack": false,
        "departurePrice": null,
        "tooltipText": "Стоимость указана за первичный приём.\nВ неё не входит стоимость дополнительных исследований и выезда на дом.",
        "seoSlotTipText": "",
        "isEnabledPromoPrice": false,
        "review": [],
        "specAccommodationIndex": null,
        "surgeryInfo": null
    },
    {
        "id": 589758,
        "isActive": false,
        "isHidden": true,
        "isFavorite": false,
        "name": "Грачева Татьяна Федоровна",
        "surname": "",
        "alias": "Gracheva_Tatyana_10",
        "sex": 2,
        "url": "/doctor/Gracheva_Tatyana_10",
        "logo": null,
        "rectangularImage": null,
        "image": "",
        "mobileImage": "",
        "tipMessage": "",
        "departure": false,
        "kidsReception": false,
        "rating": {
            "label": "Очень хороший",
            "rating": 0,
            "doctorRating": 8.6
        },
        "popularityRating": 0,
        "doctorExt": false,
        "index": 8,
        "ratingType": "stars_and_label",
        "countReviewsString": "0 отзывов",
        "countReviews": 0,
        "topReviewsPercent": 0,
        "rank": null,
        "specialities": [
            {
                "id": 67,
                "name": "Акушер",
                "alias": "akusher"
            },
            {
                "id": 72,
                "name": "Гинеколог",
                "alias": "ginekolog"
            }
        ],
        "tooltipPrices": [
            {
                "clinicAddress": "г. Ижевск, ул. Серова, д. 65",
                "price": null,
                "specialPrice": null,
                "sectorNames": "Акушер, Гинеколог"
            }
        ],
        "standardPrices": [],
        "highlight": 0,
        "clinics": {
            "96886": {
                "active": true,
                "selected": true,
                "id": 96886,
                "name": "Больница №8 Однопозова",
                "alias": "bolnitsa_8_odnopozova",
                "url": "/clinic/bolnitsa_8_odnopozova",
                "phone": "8 (495) 125-29-52",
                "price": null,
                "specialPrice": null,
                "coords": [
                    56.869569,
                    53.239428
                ],
                "isPrivateDoctor": false,
                "isRecommended": false,
                "notEmptySlots": false,
                "address": {
                    "street": "ул. Серова",
                    "house": "д. 65",
                    "fullAddress": "г. Ижевск, ул. Серова, д. 65"
                },
                "cityId": 0,
                "diagnosticsName": null,
                "diagnosticsPrice": null,
                "stations": null,
                "hasYandexCashBack": false,
                "receptionPrices": {
                    "clinic": {
                        "price": null,
                        "specialPrice": null
                    }
                },
                "isPriorityPartner": false,
                "adultsReception": 1,
                "kidsReception": 0,
                "kidsReceptionAgeRange": []
            }
        },
        "slots": [],
        "categoryId": 2,
        "categoryTitle": "Врач первой категории",
        "experience": 18,
        "degreeId": 0,
        "degreeAbbreviation": "",
        "degreeTitle": "",
        "hasPromoPrice": false,
        "hasStandardPrice": false,
        "hasYandexCashBack": false,
        "departurePrice": null,
        "tooltipText": "Стоимость указана за первичный приём.\nВ неё не входит стоимость дополнительных исследований и выезда на дом.",
        "seoSlotTipText": "",
        "isEnabledPromoPrice": false,
        "review": [],
        "specAccommodationIndex": null,
        "surgeryInfo": null
    },
    {
        "id": 589760,
        "isActive": false,
        "isHidden": true,
        "isFavorite": false,
        "name": "Александров Алексей Викторович",
        "surname": "",
        "alias": "Aleksandrov_Aleksey_6",
        "sex": 1,
        "url": "/doctor/Aleksandrov_Aleksey_6",
        "logo": null,
        "rectangularImage": null,
        "image": "",
        "mobileImage": "",
        "tipMessage": "",
        "departure": false,
        "kidsReception": false,
        "rating": {
            "label": "Превосходный",
            "rating": 0,
            "doctorRating": 8.8
        },
        "popularityRating": 0,
        "doctorExt": false,
        "index": 9,
        "ratingType": "stars_and_label",
        "countReviewsString": "0 отзывов",
        "countReviews": 0,
        "topReviewsPercent": 0,
        "rank": null,
        "specialities": [
            {
                "id": 107,
                "name": "Анестезиолог",
                "alias": "anesteziolog"
            },
            {
                "id": 250,
                "name": "Анестезиолог-реаниматолог",
                "alias": "anesteziolog-reanimatolog"
            },
            {
                "id": 204,
                "name": "Реаниматолог",
                "alias": "reanimatolog"
            }
        ],
        "tooltipPrices": [
            {
                "clinicAddress": "г. Ижевск, Воткинское шоссе, д. 81",
                "price": null,
                "specialPrice": null,
                "sectorNames": "Анестезиолог, Реаниматолог, Анестезиолог-реаниматолог"
            },
            {
                "clinicAddress": "г. Ижевск, ул. Серова, д. 65",
                "price": null,
                "specialPrice": null,
                "sectorNames": "Анестезиолог, Реаниматолог, Анестезиолог-реаниматолог"
            }
        ],
        "standardPrices": [],
        "highlight": 0,
        "clinics": {
            "96756": {
                "active": true,
                "selected": true,
                "id": 96756,
                "name": "Городская Клиническая Больница №7",
                "alias": "gorodska_klinicheskaya_bolnitsa_7",
                "url": "/clinic/gorodska_klinicheskaya_bolnitsa_7",
                "phone": "8 (495) 125-29-52",
                "price": null,
                "specialPrice": null,
                "coords": [
                    56.899026,
                    53.258221
                ],
                "isPrivateDoctor": false,
                "isRecommended": false,
                "notEmptySlots": false,
                "address": {
                    "street": "Воткинское шоссе",
                    "house": "д. 81",
                    "fullAddress": "г. Ижевск, Воткинское шоссе, д. 81"
                },
                "cityId": 0,
                "diagnosticsName": null,
                "diagnosticsPrice": null,
                "stations": null,
                "hasYandexCashBack": false,
                "receptionPrices": {
                    "clinic": {
                        "price": null,
                        "specialPrice": null
                    }
                },
                "isPriorityPartner": false,
                "adultsReception": 1,
                "kidsReception": 0,
                "kidsReceptionAgeRange": []
            },
            "96886": {
                "active": false,
                "selected": false,
                "id": 96886,
                "name": "Больница №8 Однопозова",
                "alias": "bolnitsa_8_odnopozova",
                "url": "/clinic/bolnitsa_8_odnopozova",
                "phone": "8 (495) 125-29-52",
                "price": null,
                "specialPrice": null,
                "coords": [
                    56.869569,
                    53.239428
                ],
                "isPrivateDoctor": false,
                "isRecommended": false,
                "notEmptySlots": false,
                "address": {
                    "street": "ул. Серова",
                    "house": "д. 65",
                    "fullAddress": "г. Ижевск, ул. Серова, д. 65"
                },
                "cityId": 0,
                "diagnosticsName": null,
                "diagnosticsPrice": null,
                "stations": null,
                "hasYandexCashBack": false,
                "receptionPrices": {
                    "clinic": {
                        "price": null,
                        "specialPrice": null
                    }
                },
                "isPriorityPartner": false,
                "adultsReception": 1,
                "kidsReception": 0,
                "kidsReceptionAgeRange": []
            }
        },
        "slots": [],
        "categoryId": 1,
        "categoryTitle": "Врач высшей категории",
        "experience": 29,
        "degreeId": 0,
        "degreeAbbreviation": "",
        "degreeTitle": "",
        "hasPromoPrice": false,
        "hasStandardPrice": false,
        "hasYandexCashBack": false,
        "departurePrice": null,
        "tooltipText": "Стоимость указана за первичный приём.\nВ неё не входит стоимость дополнительных исследований и выезда на дом.",
        "seoSlotTipText": "",
        "isEnabledPromoPrice": false,
        "review": [],
        "specAccommodationIndex": null,
        "surgeryInfo": null
    }
]}