{"doctors": [
    {
        "id": 592796,
        "isActive": false,
        "isHidden": true,
        "isFavorite": false,
        "name": "Осипова Елена Леонидовна",
        "surname": "",
        "alias": "Osipova_Elena_26",
        "sex": 2,
        "url": "/doctor/Osipova_Elena_26",
        "logo": null,
        "rectangularImage": null,
        "image": "",
        "mobileImage": "",
        "tipMessage": "",
        "departure": false,
        "kidsReception": false,
        "rating": {
            "label": "Превосходный",
            "rating": 0,
            "doctorRating": 8.8
        },
        "popularityRating": 0,
        "doctorExt": false,
        "index": 0,
        "ratingType": "stars_and_label",
        "countReviewsString": "0 отзывов",
        "countReviews": 0,
        "topReviewsPercent": 0,
        "rank": null,
        "specialities": [
            {
                "id": 90,
                "name": "Стоматолог",
                "alias": "stomatolog"
            }
        ],
        "tooltipPrices": [
            {
                "clinicAddress": "г. Ижевск, ул. Труда, д. 1",
                "price": null,
                "specialPrice": null,
                "sectorNames": "Стоматолог"
            },
            {
                "clinicAddress": "г. Ижевск, ул. Пушкинская, д. 136",
                "price": null,
                "specialPrice": null,
                "sectorNames": "Стоматолог"
            }
        ],
        "standardPrices": [],
        "highlight": 0,
        "clinics": {
            "97052": {
                "active": true,
                "selected": true,
                "id": 97052,
                "name": "Городская больница №6 Поликлиника №2",
                "alias": "gorodskaya_bolnitsa_6_poliklinika_2",
                "url": "/clinic/gorodskaya_bolnitsa_6_poliklinika_2",
                "phone": "8 (495) 125-29-52",
                "price": null,
                "specialPrice": null,
                "coords": [
                    56.863178,
                    53.293488
                ],
                "isPrivateDoctor": false,
                "isRecommended": false,
                "notEmptySlots": false,
                "address": {
                    "street": "ул. Труда",
                    "house": "д. 1",
                    "fullAddress": "г. Ижевск, ул. Труда, д. 1"
                },
                "cityId": 0,
                "diagnosticsName": null,
                "diagnosticsPrice": null,
                "stations": null,
                "hasYandexCashBack": false,
                "receptionPrices": {
                    "clinic": {
                        "price": null,
                        "specialPrice": null
                    }
                },
                "isPriorityPartner": false,
                "adultsReception": 1,
                "kidsReception": 0,
                "kidsReceptionAgeRange": []
            },
            "97780": {
                "active": false,
                "selected": false,
                "id": 97780,
                "name": "Городская больница №6 Стоматологическая поликлиника",
                "alias": "gorodskaya_bolnitsa_6_stomatologicheskaya_poliklinika",
                "url": "/clinic/gorodskaya_bolnitsa_6_stomatologicheskaya_poliklinika",
                "phone": "8 (495) 125-29-52",
                "price": null,
                "specialPrice": null,
                "coords": [
                    56.838578,
                    53.218264
                ],
                "isPrivateDoctor": false,
                "isRecommended": false,
                "notEmptySlots": false,
                "address": {
                    "street": "ул. Пушкинская",
                    "house": "д. 136",
                    "fullAddress": "г. Ижевск, ул. Пушкинская, д. 136"
                },
                "cityId": 0,
                "diagnosticsName": null,
                "diagnosticsPrice": null,
                "stations": null,
                "hasYandexCashBack": false,
                "receptionPrices": {
                    "clinic": {
                        "price": null,
                        "specialPrice": null
                    }
                },
                "isPriorityPartner": false,
                "adultsReception": 1,
                "kidsReception": 0,
                "kidsReceptionAgeRange": []
            }
        },
        "slots": [],
        "categoryId": 0,
        "categoryTitle": "",
        "experience": 28,
        "degreeId": 0,
        "degreeAbbreviation": "",
        "degreeTitle": "",
        "hasPromoPrice": false,
        "hasStandardPrice": false,
        "hasYandexCashBack": false,
        "departurePrice": null,
        "tooltipText": "Стоимость указана за первичный приём.\nВ неё не входит стоимость дополнительных исследований и выезда на дом.",
        "seoSlotTipText": "",
        "isEnabledPromoPrice": false,
        "review": [],
        "specAccommodationIndex": null,
        "surgeryInfo": null
    },
    {
        "id": 592804,
        "isActive": false,
        "isHidden": true,
        "isFavorite": false,
        "name": "Косарева Ирина Петровна",
        "surname": "",
        "alias": "Kosareva_Irina_4",
        "sex": 2,
        "url": "/doctor/Kosareva_Irina_4",
        "logo": null,
        "rectangularImage": null,
        "image": "https://cdn.docdoc.ru/doctor/592804_20201125180641.162x162.jpg?1669431334",
        "mobileImage": "https://cdn.docdoc.ru/doctor/592804_20201125180641.640x400.jpg?1669431334",
        "tipMessage": "",
        "departure": false,
        "kidsReception": false,
        "rating": {
            "label": "Очень хороший",
            "rating": 0,
            "doctorRating": 8.6
        },
        "popularityRating": 0,
        "doctorExt": false,
        "index": 1,
        "ratingType": "stars_and_label",
        "countReviewsString": "0 отзывов",
        "countReviews": 0,
        "topReviewsPercent": 0,
        "rank": null,
        "specialities": [
            {
                "id": 90,
                "name": "Стоматолог",
                "alias": "stomatolog"
            }
        ],
        "tooltipPrices": [
            {
                "clinicAddress": "г. Ижевск, ул. Пушкинская, д. 136",
                "price": null,
                "specialPrice": null,
                "sectorNames": "Стоматолог"
            }
        ],
        "standardPrices": [],
        "highlight": 0,
        "clinics": {
            "97780": {
                "active": true,
                "selected": true,
                "id": 97780,
                "name": "Городская больница №6 Стоматологическая поликлиника",
                "alias": "gorodskaya_bolnitsa_6_stomatologicheskaya_poliklinika",
                "url": "/clinic/gorodskaya_bolnitsa_6_stomatologicheskaya_poliklinika",
                "phone": "8 (495) 125-29-52",
                "price": null,
                "specialPrice": null,
                "coords": [
                    56.838578,
                    53.218264
                ],
                "isPrivateDoctor": false,
                "isRecommended": false,
                "notEmptySlots": false,
                "address": {
                    "street": "ул. Пушкинская",
                    "house": "д. 136",
                    "fullAddress": "г. Ижевск, ул. Пушкинская, д. 136"
                },
                "cityId": 0,
                "diagnosticsName": null,
                "diagnosticsPrice": null,
                "stations": null,
                "hasYandexCashBack": false,
                "receptionPrices": {
                    "clinic": {
                        "price": null,
                        "specialPrice": null
                    }
                },
                "isPriorityPartner": false,
                "adultsReception": 1,
                "kidsReception": 0,
                "kidsReceptionAgeRange": []
            }
        },
        "slots": [],
        "categoryId": 2,
        "categoryTitle": "Врач первой категории",
        "experience": 22,
        "degreeId": 0,
        "degreeAbbreviation": "",
        "degreeTitle": "",
        "hasPromoPrice": false,
        "hasStandardPrice": false,
        "hasYandexCashBack": false,
        "departurePrice": null,
        "tooltipText": "Стоимость указана за первичный приём.\nВ неё не входит стоимость дополнительных исследований и выезда на дом.",
        "seoSlotTipText": "",
        "isEnabledPromoPrice": false,
        "review": [],
        "specAccommodationIndex": null,
        "surgeryInfo": null
    },
    {
        "id": 592820,
        "isActive": false,
        "isHidden": true,
        "isFavorite": false,
        "name": "Казакова Ольга Анатольевна",
        "surname": "",
        "alias": "Kazakova_Olga_19",
        "sex": 2,
        "url": "/doctor/Kazakova_Olga_19",
        "logo": null,
        "rectangularImage": null,
        "image": "",
        "mobileImage": "",
        "tipMessage": "",
        "departure": false,
        "kidsReception": false,
        "rating": {
            "label": "Очень хороший",
            "rating": 0,
            "doctorRating": 8.6
        },
        "popularityRating": 0,
        "doctorExt": false,
        "index": 2,
        "ratingType": "stars_and_label",
        "countReviewsString": "0 отзывов",
        "countReviews": 0,
        "topReviewsPercent": 0,
        "rank": null,
        "specialities": [
            {
                "id": 90,
                "name": "Стоматолог",
                "alias": "stomatolog"
            }
        ],
        "tooltipPrices": [
            {
                "clinicAddress": "г. Ижевск, ул. Труда, д. 1",
                "price": null,
                "specialPrice": null,
                "sectorNames": "Стоматолог"
            },
            {
                "clinicAddress": "г. Ижевск, ул. Пушкинская, д. 136",
                "price": null,
                "specialPrice": null,
                "sectorNames": "Стоматолог"
            }
        ],
        "standardPrices": [],
        "highlight": 0,
        "clinics": {
            "97052": {
                "active": true,
                "selected": true,
                "id": 97052,
                "name": "Городская больница №6 Поликлиника №2",
                "alias": "gorodskaya_bolnitsa_6_poliklinika_2",
                "url": "/clinic/gorodskaya_bolnitsa_6_poliklinika_2",
                "phone": "8 (495) 125-29-52",
                "price": null,
                "specialPrice": null,
                "coords": [
                    56.863178,
                    53.293488
                ],
                "isPrivateDoctor": false,
                "isRecommended": false,
                "notEmptySlots": false,
                "address": {
                    "street": "ул. Труда",
                    "house": "д. 1",
                    "fullAddress": "г. Ижевск, ул. Труда, д. 1"
                },
                "cityId": 0,
                "diagnosticsName": null,
                "diagnosticsPrice": null,
                "stations": null,
                "hasYandexCashBack": false,
                "receptionPrices": {
                    "clinic": {
                        "price": null,
                        "specialPrice": null
                    }
                },
                "isPriorityPartner": false,
                "adultsReception": 1,
                "kidsReception": 0,
                "kidsReceptionAgeRange": []
            },
            "97780": {
                "active": false,
                "selected": false,
                "id": 97780,
                "name": "Городская больница №6 Стоматологическая поликлиника",
                "alias": "gorodskaya_bolnitsa_6_stomatologicheskaya_poliklinika",
                "url": "/clinic/gorodskaya_bolnitsa_6_stomatologicheskaya_poliklinika",
                "phone": "8 (495) 125-29-52",
                "price": null,
                "specialPrice": null,
                "coords": [
                    56.838578,
                    53.218264
                ],
                "isPrivateDoctor": false,
                "isRecommended": false,
                "notEmptySlots": false,
                "address": {
                    "street": "ул. Пушкинская",
                    "house": "д. 136",
                    "fullAddress": "г. Ижевск, ул. Пушкинская, д. 136"
                },
                "cityId": 0,
                "diagnosticsName": null,
                "diagnosticsPrice": null,
                "stations": null,
                "hasYandexCashBack": false,
                "receptionPrices": {
                    "clinic": {
                        "price": null,
                        "specialPrice": null
                    }
                },
                "isPriorityPartner": false,
                "adultsReception": 1,
                "kidsReception": 0,
                "kidsReceptionAgeRange": []
            }
        },
        "slots": [],
        "categoryId": 2,
        "categoryTitle": "Врач первой категории",
        "experience": 30,
        "degreeId": 0,
        "degreeAbbreviation": "",
        "degreeTitle": "",
        "hasPromoPrice": false,
        "hasStandardPrice": false,
        "hasYandexCashBack": false,
        "departurePrice": null,
        "tooltipText": "Стоимость указана за первичный приём.\nВ неё не входит стоимость дополнительных исследований и выезда на дом.",
        "seoSlotTipText": "",
        "isEnabledPromoPrice": false,
        "review": [],
        "specAccommodationIndex": null,
        "surgeryInfo": null
    },
    {
        "id": 592828,
        "isActive": false,
        "isHidden": true,
        "isFavorite": false,
        "name": "Лисин Владимир Иванович",
        "surname": "",
        "alias": "Lisin_Vladimir",
        "sex": 1,
        "url": "/doctor/Lisin_Vladimir",
        "logo": null,
        "rectangularImage": null,
        "image": "https://cdn.docdoc.ru/doctor/592828_20201125181554.162x162.jpg?1669431335",
        "mobileImage": "https://cdn.docdoc.ru/doctor/592828_20201125181554.640x400.jpg?1669431335",
        "tipMessage": "",
        "departure": false,
        "kidsReception": false,
        "rating": {
            "label": "Очень хороший",
            "rating": 0,
            "doctorRating": 8.6
        },
        "popularityRating": 0,
        "doctorExt": false,
        "index": 3,
        "ratingType": "stars_and_label",
        "countReviewsString": "0 отзывов",
        "countReviews": 0,
        "topReviewsPercent": 0,
        "rank": null,
        "specialities": [
            {
                "id": 90,
                "name": "Стоматолог",
                "alias": "stomatolog"
            },
            {
                "id": 121,
                "name": "Стоматолог-ортопед",
                "alias": "stomatolog-ortoped"
            }
        ],
        "tooltipPrices": [
            {
                "clinicAddress": "г. Ижевск, ул. Пушкинская, д. 136",
                "price": null,
                "specialPrice": null,
                "sectorNames": "Стоматолог, Стоматолог-ортопед"
            }
        ],
        "standardPrices": [],
        "highlight": 0,
        "clinics": {
            "97780": {
                "active": true,
                "selected": true,
                "id": 97780,
                "name": "Городская больница №6 Стоматологическая поликлиника",
                "alias": "gorodskaya_bolnitsa_6_stomatologicheskaya_poliklinika",
                "url": "/clinic/gorodskaya_bolnitsa_6_stomatologicheskaya_poliklinika",
                "phone": "8 (495) 125-29-52",
                "price": null,
                "specialPrice": null,
                "coords": [
                    56.838578,
                    53.218264
                ],
                "isPrivateDoctor": false,
                "isRecommended": false,
                "notEmptySlots": false,
                "address": {
                    "street": "ул. Пушкинская",
                    "house": "д. 136",
                    "fullAddress": "г. Ижевск, ул. Пушкинская, д. 136"
                },
                "cityId": 0,
                "diagnosticsName": null,
                "diagnosticsPrice": null,
                "stations": null,
                "hasYandexCashBack": false,
                "receptionPrices": {
                    "clinic": {
                        "price": null,
                        "specialPrice": null
                    }
                },
                "isPriorityPartner": false,
                "adultsReception": 1,
                "kidsReception": 0,
                "kidsReceptionAgeRange": []
            }
        },
        "slots": [],
        "categoryId": 1,
        "categoryTitle": "Врач высшей категории",
        "experience": 42,
        "degreeId": 0,
        "degreeAbbreviation": "",
        "degreeTitle": "",
        "hasPromoPrice": false,
        "hasStandardPrice": false,
        "hasYandexCashBack": false,
        "departurePrice": null,
        "tooltipText": "Стоимость указана за первичный приём.\nВ неё не входит стоимость дополнительных исследований и выезда на дом.",
        "seoSlotTipText": "",
        "isEnabledPromoPrice": false,
        "review": [],
        "specAccommodationIndex": null,
        "surgeryInfo": null
    },
    {
        "id": 592830,
        "isActive": false,
        "isHidden": true,
        "isFavorite": false,
        "name": "Главатских Надежда Геннадьевна",
        "surname": "",
        "alias": "Glavatskih_Nadezhda",
        "sex": 2,
        "url": "/doctor/Glavatskih_Nadezhda",
        "logo": null,
        "rectangularImage": null,
        "image": "https://cdn.docdoc.ru/doctor/592830_20201125182051.162x162.jpg?1669431335",
        "mobileImage": "https://cdn.docdoc.ru/doctor/592830_20201125182051.640x400.jpg?1669431335",
        "tipMessage": "",
        "departure": false,
        "kidsReception": false,
        "rating": {
            "label": "Очень хороший",
            "rating": 0,
            "doctorRating": 8.6
        },
        "popularityRating": 0,
        "doctorExt": false,
        "index": 4,
        "ratingType": "stars_and_label",
        "countReviewsString": "0 отзывов",
        "countReviews": 0,
        "topReviewsPercent": 0,
        "rank": null,
        "specialities": [
            {
                "id": 90,
                "name": "Стоматолог",
                "alias": "stomatolog"
            }
        ],
        "tooltipPrices": [
            {
                "clinicAddress": "г. Ижевск, ул. Пушкинская, д. 136",
                "price": null,
                "specialPrice": null,
                "sectorNames": "Стоматолог"
            }
        ],
        "standardPrices": [],
        "highlight": 0,
        "clinics": {
            "97780": {
                "active": true,
                "selected": true,
                "id": 97780,
                "name": "Городская больница №6 Стоматологическая поликлиника",
                "alias": "gorodskaya_bolnitsa_6_stomatologicheskaya_poliklinika",
                "url": "/clinic/gorodskaya_bolnitsa_6_stomatologicheskaya_poliklinika",
                "phone": "8 (495) 125-29-52",
                "price": null,
                "specialPrice": null,
                "coords": [
                    56.838578,
                    53.218264
                ],
                "isPrivateDoctor": false,
                "isRecommended": false,
                "notEmptySlots": false,
                "address": {
                    "street": "ул. Пушкинская",
                    "house": "д. 136",
                    "fullAddress": "г. Ижевск, ул. Пушкинская, д. 136"
                },
                "cityId": 0,
                "diagnosticsName": null,
                "diagnosticsPrice": null,
                "stations": null,
                "hasYandexCashBack": false,
                "receptionPrices": {
                    "clinic": {
                        "price": null,
                        "specialPrice": null
                    }
                },
                "isPriorityPartner": false,
                "adultsReception": 1,
                "kidsReception": 0,
                "kidsReceptionAgeRange": []
            }
        },
        "slots": [],
        "categoryId": 1,
        "categoryTitle": "Врач высшей категории",
        "experience": 33,
        "degreeId": 0,
        "degreeAbbreviation": "",
        "degreeTitle": "",
        "hasPromoPrice": false,
        "hasStandardPrice": false,
        "hasYandexCashBack": false,
        "departurePrice": null,
        "tooltipText": "Стоимость указана за первичный приём.\nВ неё не входит стоимость дополнительных исследований и выезда на дом.",
        "seoSlotTipText": "",
        "isEnabledPromoPrice": false,
        "review": [],
        "specAccommodationIndex": null,
        "surgeryInfo": null
    },
    {
        "id": 592832,
        "isActive": false,
        "isHidden": true,
        "isFavorite": false,
        "name": "Попова Виктория Алексеевна",
        "surname": "",
        "alias": "Popova_Viktoriya_10",
        "sex": 2,
        "url": "/doctor/Popova_Viktoriya_10",
        "logo": null,
        "rectangularImage": null,
        "image": "",
        "mobileImage": "",
        "tipMessage": "",
        "departure": false,
        "kidsReception": false,
        "rating": {
            "label": "Очень хороший",
            "rating": 0,
            "doctorRating": 8
        },
        "popularityRating": 0,
        "doctorExt": false,
        "index": 5,
        "ratingType": "stars_and_label",
        "countReviewsString": "0 отзывов",
        "countReviews": 0,
        "topReviewsPercent": 0,
        "rank": null,
        "specialities": [
            {
                "id": 90,
                "name": "Стоматолог",
                "alias": "stomatolog"
            }
        ],
        "tooltipPrices": [
            {
                "clinicAddress": "г. Ижевск, ул. Пушкинская, д. 136",
                "price": null,
                "specialPrice": null,
                "sectorNames": "Стоматолог"
            }
        ],
        "standardPrices": [],
        "highlight": 0,
        "clinics": {
            "97780": {
                "active": true,
                "selected": true,
                "id": 97780,
                "name": "Городская больница №6 Стоматологическая поликлиника",
                "alias": "gorodskaya_bolnitsa_6_stomatologicheskaya_poliklinika",
                "url": "/clinic/gorodskaya_bolnitsa_6_stomatologicheskaya_poliklinika",
                "phone": "8 (495) 125-29-52",
                "price": null,
                "specialPrice": null,
                "coords": [
                    56.838578,
                    53.218264
                ],
                "isPrivateDoctor": false,
                "isRecommended": false,
                "notEmptySlots": false,
                "address": {
                    "street": "ул. Пушкинская",
                    "house": "д. 136",
                    "fullAddress": "г. Ижевск, ул. Пушкинская, д. 136"
                },
                "cityId": 0,
                "diagnosticsName": null,
                "diagnosticsPrice": null,
                "stations": null,
                "hasYandexCashBack": false,
                "receptionPrices": {
                    "clinic": {
                        "price": null,
                        "specialPrice": null
                    }
                },
                "isPriorityPartner": false,
                "adultsReception": 1,
                "kidsReception": 0,
                "kidsReceptionAgeRange": []
            }
        },
        "slots": [],
        "categoryId": 0,
        "categoryTitle": "",
        "experience": 3,
        "degreeId": 0,
        "degreeAbbreviation": "",
        "degreeTitle": "",
        "hasPromoPrice": false,
        "hasStandardPrice": false,
        "hasYandexCashBack": false,
        "departurePrice": null,
        "tooltipText": "Стоимость указана за первичный приём.\nВ неё не входит стоимость дополнительных исследований и выезда на дом.",
        "seoSlotTipText": "",
        "isEnabledPromoPrice": false,
        "review": [],
        "specAccommodationIndex": null,
        "surgeryInfo": null
    },
    {
        "id": 592836,
        "isActive": false,
        "isHidden": true,
        "isFavorite": false,
        "name": "Арзамасов Николай Арсентьевич",
        "surname": "",
        "alias": "Arzamasov_Nikolay",
        "sex": 1,
        "url": "/doctor/Arzamasov_Nikolay",
        "logo": null,
        "rectangularImage": null,
        "image": "https://cdn.docdoc.ru/doctor/592836_20201125183019.162x162.jpg?1669431335",
        "mobileImage": "https://cdn.docdoc.ru/doctor/592836_20201125183019.640x400.jpg?1669431335",
        "tipMessage": "",
        "departure": false,
        "kidsReception": false,
        "rating": {
            "label": "Превосходный",
            "rating": 0,
            "doctorRating": 8.8
        },
        "popularityRating": 0,
        "doctorExt": false,
        "index": 6,
        "ratingType": "stars_and_label",
        "countReviewsString": "0 отзывов",
        "countReviews": 0,
        "topReviewsPercent": 0,
        "rank": null,
        "specialities": [
            {
                "id": 90,
                "name": "Стоматолог",
                "alias": "stomatolog"
            },
            {
                "id": 121,
                "name": "Стоматолог-ортопед",
                "alias": "stomatolog-ortoped"
            }
        ],
        "tooltipPrices": [
            {
                "clinicAddress": "г. Ижевск, ул. Пушкинская, д. 136",
                "price": null,
                "specialPrice": null,
                "sectorNames": "Стоматолог, Стоматолог-ортопед"
            }
        ],
        "standardPrices": [],
        "highlight": 0,
        "clinics": {
            "97780": {
                "active": true,
                "selected": true,
                "id": 97780,
                "name": "Городская больница №6 Стоматологическая поликлиника",
                "alias": "gorodskaya_bolnitsa_6_stomatologicheskaya_poliklinika",
                "url": "/clinic/gorodskaya_bolnitsa_6_stomatologicheskaya_poliklinika",
                "phone": "8 (495) 125-29-52",
                "price": null,
                "specialPrice": null,
                "coords": [
                    56.838578,
                    53.218264
                ],
                "isPrivateDoctor": false,
                "isRecommended": false,
                "notEmptySlots": false,
                "address": {
                    "street": "ул. Пушкинская",
                    "house": "д. 136",
                    "fullAddress": "г. Ижевск, ул. Пушкинская, д. 136"
                },
                "cityId": 0,
                "diagnosticsName": null,
                "diagnosticsPrice": null,
                "stations": null,
                "hasYandexCashBack": false,
                "receptionPrices": {
                    "clinic": {
                        "price": null,
                        "specialPrice": null
                    }
                },
                "isPriorityPartner": false,
                "adultsReception": 1,
                "kidsReception": 0,
                "kidsReceptionAgeRange": []
            }
        },
        "slots": [],
        "categoryId": 3,
        "categoryTitle": "Врач второй категории",
        "experience": 36,
        "degreeId": 0,
        "degreeAbbreviation": "",
        "degreeTitle": "",
        "hasPromoPrice": false,
        "hasStandardPrice": false,
        "hasYandexCashBack": false,
        "departurePrice": null,
        "tooltipText": "Стоимость указана за первичный приём.\nВ неё не входит стоимость дополнительных исследований и выезда на дом.",
        "seoSlotTipText": "",
        "isEnabledPromoPrice": false,
        "review": [],
        "specAccommodationIndex": null,
        "surgeryInfo": null
    },
    {
        "id": 592840,
        "isActive": false,
        "isHidden": true,
        "isFavorite": false,
        "name": "Смирнова Светлана Юрьевна",
        "surname": "",
        "alias": "Smirnova_Svetlana_38",
        "sex": 2,
        "url": "/doctor/Smirnova_Svetlana_38",
        "logo": null,
        "rectangularImage": null,
        "image": "https://cdn.docdoc.ru/doctor/592840_20201125183821.162x162.jpg?1669431335",
        "mobileImage": "https://cdn.docdoc.ru/doctor/592840_20201125183821.640x400.jpg?1669431335",
        "tipMessage": "",
        "departure": false,
        "kidsReception": false,
        "rating": {
            "label": "Очень хороший",
            "rating": 0,
            "doctorRating": 8.6
        },
        "popularityRating": 0,
        "doctorExt": false,
        "index": 7,
        "ratingType": "stars_and_label",
        "countReviewsString": "0 отзывов",
        "countReviews": 0,
        "topReviewsPercent": 0,
        "rank": null,
        "specialities": [
            {
                "id": 90,
                "name": "Стоматолог",
                "alias": "stomatolog"
            }
        ],
        "tooltipPrices": [
            {
                "clinicAddress": "г. Ижевск, ул. Пушкинская, д. 136",
                "price": null,
                "specialPrice": null,
                "sectorNames": "Стоматолог"
            }
        ],
        "standardPrices": [],
        "highlight": 0,
        "clinics": {
            "97780": {
                "active": true,
                "selected": true,
                "id": 97780,
                "name": "Городская больница №6 Стоматологическая поликлиника",
                "alias": "gorodskaya_bolnitsa_6_stomatologicheskaya_poliklinika",
                "url": "/clinic/gorodskaya_bolnitsa_6_stomatologicheskaya_poliklinika",
                "phone": "8 (495) 125-29-52",
                "price": null,
                "specialPrice": null,
                "coords": [
                    56.838578,
                    53.218264
                ],
                "isPrivateDoctor": false,
                "isRecommended": false,
                "notEmptySlots": false,
                "address": {
                    "street": "ул. Пушкинская",
                    "house": "д. 136",
                    "fullAddress": "г. Ижевск, ул. Пушкинская, д. 136"
                },
                "cityId": 0,
                "diagnosticsName": null,
                "diagnosticsPrice": null,
                "stations": null,
                "hasYandexCashBack": false,
                "receptionPrices": {
                    "clinic": {
                        "price": null,
                        "specialPrice": null
                    }
                },
                "isPriorityPartner": false,
                "adultsReception": 1,
                "kidsReception": 0,
                "kidsReceptionAgeRange": []
            }
        },
        "slots": [],
        "categoryId": 3,
        "categoryTitle": "Врач второй категории",
        "experience": 34,
        "degreeId": 0,
        "degreeAbbreviation": "",
        "degreeTitle": "",
        "hasPromoPrice": false,
        "hasStandardPrice": false,
        "hasYandexCashBack": false,
        "departurePrice": null,
        "tooltipText": "Стоимость указана за первичный приём.\nВ неё не входит стоимость дополнительных исследований и выезда на дом.",
        "seoSlotTipText": "",
        "isEnabledPromoPrice": false,
        "review": [],
        "specAccommodationIndex": null,
        "surgeryInfo": null
    },
    {
        "id": 592850,
        "isActive": false,
        "isHidden": true,
        "isFavorite": false,
        "name": "Маркова Ирина Валерьевна",
        "surname": "",
        "alias": "Markova_Irina_8",
        "sex": 2,
        "url": "/doctor/Markova_Irina_8",
        "logo": null,
        "rectangularImage": null,
        "image": "",
        "mobileImage": "",
        "tipMessage": "",
        "departure": false,
        "kidsReception": false,
        "rating": {
            "label": "Очень хороший",
            "rating": 0,
            "doctorRating": 8.6
        },
        "popularityRating": 0,
        "doctorExt": false,
        "index": 8,
        "ratingType": "stars_and_label",
        "countReviewsString": "0 отзывов",
        "countReviews": 0,
        "topReviewsPercent": 0,
        "rank": null,
        "specialities": [
            {
                "id": 90,
                "name": "Стоматолог",
                "alias": "stomatolog"
            }
        ],
        "tooltipPrices": [
            {
                "clinicAddress": "г. Ижевск, ул. Пушкинская, д. 136",
                "price": null,
                "specialPrice": null,
                "sectorNames": "Стоматолог"
            }
        ],
        "standardPrices": [],
        "highlight": 0,
        "clinics": {
            "97780": {
                "active": true,
                "selected": true,
                "id": 97780,
                "name": "Городская больница №6 Стоматологическая поликлиника",
                "alias": "gorodskaya_bolnitsa_6_stomatologicheskaya_poliklinika",
                "url": "/clinic/gorodskaya_bolnitsa_6_stomatologicheskaya_poliklinika",
                "phone": "8 (495) 125-29-52",
                "price": null,
                "specialPrice": null,
                "coords": [
                    56.838578,
                    53.218264
                ],
                "isPrivateDoctor": false,
                "isRecommended": false,
                "notEmptySlots": false,
                "address": {
                    "street": "ул. Пушкинская",
                    "house": "д. 136",
                    "fullAddress": "г. Ижевск, ул. Пушкинская, д. 136"
                },
                "cityId": 0,
                "diagnosticsName": null,
                "diagnosticsPrice": null,
                "stations": null,
                "hasYandexCashBack": false,
                "receptionPrices": {
                    "clinic": {
                        "price": null,
                        "specialPrice": null
                    }
                },
                "isPriorityPartner": false,
                "adultsReception": 1,
                "kidsReception": 0,
                "kidsReceptionAgeRange": []
            }
        },
        "slots": [],
        "categoryId": 0,
        "categoryTitle": "",
        "experience": 34,
        "degreeId": 0,
        "degreeAbbreviation": "",
        "degreeTitle": "",
        "hasPromoPrice": false,
        "hasStandardPrice": false,
        "hasYandexCashBack": false,
        "departurePrice": null,
        "tooltipText": "Стоимость указана за первичный приём.\nВ неё не входит стоимость дополнительных исследований и выезда на дом.",
        "seoSlotTipText": "",
        "isEnabledPromoPrice": false,
        "review": [],
        "specAccommodationIndex": null,
        "surgeryInfo": null
    },
    {
        "id": 592886,
        "isActive": false,
        "isHidden": true,
        "isFavorite": false,
        "name": "Медведева Мария Дмитриевна",
        "surname": "",
        "alias": "Medvedeva_Mariya_11",
        "sex": 2,
        "url": "/doctor/Medvedeva_Mariya_11",
        "logo": null,
        "rectangularImage": null,
        "image": "",
        "mobileImage": "",
        "tipMessage": "",
        "departure": false,
        "kidsReception": false,
        "rating": {
            "label": "Очень хороший",
            "rating": 0,
            "doctorRating": 8.4
        },
        "popularityRating": 0,
        "doctorExt": false,
        "index": 9,
        "ratingType": "stars_and_label",
        "countReviewsString": "0 отзывов",
        "countReviews": 0,
        "topReviewsPercent": 0,
        "rank": null,
        "specialities": [
            {
                "id": 90,
                "name": "Стоматолог",
                "alias": "stomatolog"
            },
            {
                "id": 127,
                "name": "Стоматолог-хирург",
                "alias": "stomatolog-hirurg"
            }
        ],
        "tooltipPrices": [
            {
                "clinicAddress": "г. Ижевск, ул. Труда, д. 1",
                "price": null,
                "specialPrice": null,
                "sectorNames": "Стоматолог, Стоматолог-хирург"
            },
            {
                "clinicAddress": "г. Ижевск, ул. Пушкинская, д. 136",
                "price": null,
                "specialPrice": null,
                "sectorNames": "Стоматолог, Стоматолог-хирург"
            }
        ],
        "standardPrices": [],
        "highlight": 0,
        "clinics": {
            "97052": {
                "active": true,
                "selected": true,
                "id": 97052,
                "name": "Городская больница №6 Поликлиника №2",
                "alias": "gorodskaya_bolnitsa_6_poliklinika_2",
                "url": "/clinic/gorodskaya_bolnitsa_6_poliklinika_2",
                "phone": "8 (495) 125-29-52",
                "price": null,
                "specialPrice": null,
                "coords": [
                    56.863178,
                    53.293488
                ],
                "isPrivateDoctor": false,
                "isRecommended": false,
                "notEmptySlots": false,
                "address": {
                    "street": "ул. Труда",
                    "house": "д. 1",
                    "fullAddress": "г. Ижевск, ул. Труда, д. 1"
                },
                "cityId": 0,
                "diagnosticsName": null,
                "diagnosticsPrice": null,
                "stations": null,
                "hasYandexCashBack": false,
                "receptionPrices": {
                    "clinic": {
                        "price": null,
                        "specialPrice": null
                    }
                },
                "isPriorityPartner": false,
                "adultsReception": 1,
                "kidsReception": 0,
                "kidsReceptionAgeRange": []
            },
            "97780": {
                "active": false,
                "selected": false,
                "id": 97780,
                "name": "Городская больница №6 Стоматологическая поликлиника",
                "alias": "gorodskaya_bolnitsa_6_stomatologicheskaya_poliklinika",
                "url": "/clinic/gorodskaya_bolnitsa_6_stomatologicheskaya_poliklinika",
                "phone": "8 (495) 125-29-52",
                "price": null,
                "specialPrice": null,
                "coords": [
                    56.838578,
                    53.218264
                ],
                "isPrivateDoctor": false,
                "isRecommended": false,
                "notEmptySlots": false,
                "address": {
                    "street": "ул. Пушкинская",
                    "house": "д. 136",
                    "fullAddress": "г. Ижевск, ул. Пушкинская, д. 136"
                },
                "cityId": 0,
                "diagnosticsName": null,
                "diagnosticsPrice": null,
                "stations": null,
                "hasYandexCashBack": false,
                "receptionPrices": {
                    "clinic": {
                        "price": null,
                        "specialPrice": null
                    }
                },
                "isPriorityPartner": false,
                "adultsReception": 1,
                "kidsReception": 0,
                "kidsReceptionAgeRange": []
            }
        },
        "slots": [],
        "categoryId": 0,
        "categoryTitle": "",
        "experience": 8,
        "degreeId": 0,
        "degreeAbbreviation": "",
        "degreeTitle": "",
        "hasPromoPrice": false,
        "hasStandardPrice": false,
        "hasYandexCashBack": false,
        "departurePrice": null,
        "tooltipText": "Стоимость указана за первичный приём.\nВ неё не входит стоимость дополнительных исследований и выезда на дом.",
        "seoSlotTipText": "",
        "isEnabledPromoPrice": false,
        "review": [],
        "specAccommodationIndex": null,
        "surgeryInfo": null
    }
]}